buzzsprout_client/__init__.py
buzzsprout_client/client.py
buzzsprout_client-0.2.0.dist-info/LICENSE
buzzsprout_client-0.2.0.dist-info/METADATA
buzzsprout_client-0.2.0.dist-info/WHEEL
buzzsprout_client-0.2.0.dist-info/RECORD
