Metadata-Version: 2.3
Name: buzzsprout-client
Version: 0.2.0
Summary: Python client for Buzzsprout API
License: MIT
Author: Peter Labaj
Author-email: peter.labaj@gmail.com
Requires-Python: >=3.8,<4.0
Classifier: License :: OSI Approved :: MIT License
Classifier: Programming Language :: Python :: 3
Classifier: Programming Language :: Python :: 3.8
Classifier: Programming Language :: Python :: 3.9
Classifier: Programming Language :: Python :: 3.10
Classifier: Programming Language :: Python :: 3.11
Classifier: Programming Language :: Python :: 3.12
Classifier: Programming Language :: Python :: 3.13
Requires-Dist: requests (>=2.28.0,<3.0.0)
Project-URL: Homepage, https://github.com/plabaj/buzzsprout-client
